restsuite/__init__.py
restsuite/base_rest.py
restsuite/rest.py
restsuite/restlet.py
restsuite/suiteql.py
restsuite-1.0.0.dist-info/LICENSE
restsuite-1.0.0.dist-info/METADATA
restsuite-1.0.0.dist-info/WHEEL
restsuite-1.0.0.dist-info/top_level.txt
restsuite-1.0.0.dist-info/RECORD
