Metadata-Version: 2.1
Name: restsuite
Version: 1.0.0
Summary: Easily work with Netsuite's REST API
Author: Peter Williams, Richard Demke, Andy Gannaway
Author-email: Peter Williams <petercw94@gmail.com>
License: MIT License
Project-URL: Homepage, https://github.com/Petercw94/restsuite
Keywords: netsuite,oauth,rest
Classifier: License :: OSI Approved :: MIT License
Classifier: Programming Language :: Python
Classifier: Programming Language :: Python :: 3
Classifier: Development Status :: 3 - Alpha
Classifier: Intended Audience :: Developers
Requires-Python: >=3.8
License-File: LICENSE
Requires-Dist: requests
Requires-Dist: requests-oauthlib
